auto_detail/auto_detail_main.py
auto_detail/backend.py
auto_detail/cli.py
auto_detail/config.py
auto_detail/tests/conftest.py
auto_detail/tests/test_auto_detail.py
auto_detail-0.5.0.dist-info/LICENSE
auto_detail-0.5.0.dist-info/METADATA
auto_detail-0.5.0.dist-info/WHEEL
auto_detail-0.5.0.dist-info/entry_points.txt
auto_detail-0.5.0.dist-info/RECORD
