Metadata-Version: 2.3
Name: auto-detail
Version: 0.5.0
Summary: This tool automatically generates PR details via an AI.
Author: David Wu
Author-email: 3udavid@gmail.com
Requires-Python: >=3.10,<4.0
Classifier: Programming Language :: Python :: 3
Classifier: Programming Language :: Python :: 3.10
Classifier: Programming Language :: Python :: 3.11
Classifier: Programming Language :: Python :: 3.12
Classifier: Programming Language :: Python :: 3.13
Requires-Dist: click (>=8.2.1,<9.0.0)
Requires-Dist: gitpython (>=3.1.45,<4.0.0)
Requires-Dist: google-genai (>=1.32.0,<2.0.0)
Requires-Dist: inquirerpy (>=0.3.4,<0.4.0)
Requires-Dist: pyyaml (>=6.0.2,<7.0.0)
Requires-Dist: tomli-w (>=1.2.0,<2.0.0)
